kumir/__init__.py
kumir/fil_analyze.py
kumir/robot.py
kumir_package-0.1.1.dist-info/METADATA
kumir_package-0.1.1.dist-info/WHEEL
kumir_package-0.1.1.dist-info/top_level.txt
kumir_package-0.1.1.dist-info/RECORD
