Metadata-Version: 2.4
Name: kumir-package
Version: 0.1.1
Home-page: https://github.com/vovmomyt/kumir
Author: arli
Author-email: vovmomyt <volodya.artemev.1999@mail.ru>
Requires-Python: >=3.6
Dynamic: author
Dynamic: home-page
Dynamic: requires-python
